pipmore/__init__.py
pipmore/cli.py
pipmore/package.py
pipmore/pyversion.py
pipmore-1.1.1.dist-info/LICENSE
pipmore-1.1.1.dist-info/METADATA
pipmore-1.1.1.dist-info/WHEEL
pipmore-1.1.1.dist-info/entry_points.txt
pipmore-1.1.1.dist-info/top_level.txt
pipmore-1.1.1.dist-info/RECORD
