Metadata-Version: 2.1
Name: pipmore
Version: 1.1.1
Summary: Find the latest package version supported by a specific python version
Author: Andrea Grillo
Author-email: andrea.grillo96@live.com
Maintainer-email: Andrea Grillo <andrea.grillo96@live.com>
License: Apache License
Project-URL: Source Code, https://github.com/andregri/pipmore
Project-URL: Issue Tracker, https://github.com/andregri/pipmore/issues
Keywords: version,package,pypi
Classifier: Programming Language :: Python
License-File: LICENSE
Requires-Dist: requests
